{"added": {"sculk": {"name": "Sculk"}, "frogspawn": {"name": "Frogspawn"}, "mangrove_leaves": {"name": "Mangrove Leaves"}, "mangrove_log": {"name": "Mangrove Log"}, "mangrove_planks": {"name": "Mangrove Planks"}, "mangrove_propagule": {"name": "Mangrove Propagule"}, "mangrove_roots": {"name": "Mangrove Roots"}, "mangrove_wood": {"name": "Mangrove Wood"}, "mud": {"name": "Mud"}, "mud_bricks": {"name": "Mud Bricks"}, "muddy_mangrove_roots": {"name": "Muddy Mangrove Roots"}, "ochre_froglight": {"name": "Ochre Froglight"}, "packed_mud": {"name": "Packed Mud"}, "pearlescent_froglight": {"name": "Pearlescent Froglight"}, "reinforced_deepslate": {"name": "Reinforced Deepslate"}, "sculk_catalyst": {"name": "Sculk Catalyst"}, "sculk_shrieker": {"name": "Sculk Shrieker"}, "sculk_vein": {"name": "Sculk Vein"}, "stripped_mangrove_log": {"name": "Stripped Mangrove Log"}, "stripped_mangrove_wood": {"name": "Stripped Mangrove Wood"}, "verdant_froglight": {"name": "Verdant Froglight"}}, "base": "1.18.2"}
